whl_deploy/__init__.py
whl_deploy/cli.py
whl_deploy/core/__init__.py
whl_deploy/core/base.py
whl_deploy/core/orchestrator.py
whl_deploy/steps/__init__.py
whl_deploy/steps/artifacts/__init__.py
whl_deploy/steps/artifacts/deploy/__init__.py
whl_deploy/steps/artifacts/deploy/bundle.py
whl_deploy/steps/artifacts/deploy/code.py
whl_deploy/steps/artifacts/deploy/data.py
whl_deploy/steps/artifacts/deploy/docker.py
whl_deploy/steps/artifacts/pack/__init__.py
whl_deploy/steps/artifacts/pack/bundle.py
whl_deploy/steps/artifacts/pack/code.py
whl_deploy/steps/artifacts/pack/data.py
whl_deploy/steps/artifacts/pack/docker.py
whl_deploy/steps/execution/__init__.py
whl_deploy/steps/execution/scripts.py
whl_deploy/steps/system/__init__.py
whl_deploy/steps/system/docker_setup.py
whl_deploy/steps/system/nvidia_container_setup.py
whl_deploy/utils/archive_manager.py
whl_deploy/utils/common.py
whl_deploy/utils/file_loader.py
whl_deploy/utils/prompt.py
whl_deploy/utils/system.py
whl_deploy-0.0.6.dist-info/licenses/LICENSE
whl_deploy-0.0.6.dist-info/METADATA
whl_deploy-0.0.6.dist-info/WHEEL
whl_deploy-0.0.6.dist-info/entry_points.txt
whl_deploy-0.0.6.dist-info/top_level.txt
whl_deploy-0.0.6.dist-info/RECORD
