Metadata-Version: 2.4
Name: whl-deploy
Version: 0.0.6
Summary: A deployment tool for WheelOS.
Author-email: daohu527 <support@wheelos.cn>
Project-URL: Homepage, https://github.com/wheelos-tools/whl-deploy
Project-URL: Bug Tracker, https://github.com/wheelos-tools/whl-deploy/issues
Keywords: whl-deploy,wheelos,cli-tool
Classifier: Development Status :: 3 - Alpha
Classifier: Programming Language :: Python :: 3
Classifier: Programming Language :: Python :: 3.8
Classifier: Programming Language :: Python :: 3.9
Classifier: Programming Language :: Python :: 3.10
Classifier: Programming Language :: Python :: 3.11
Classifier: Programming Language :: Python :: 3.12
Classifier: Programming Language :: Python :: 3 :: Only
Classifier: License :: OSI Approved :: MIT License
Classifier: Operating System :: POSIX :: Linux
Classifier: Intended Audience :: Developers
Classifier: Topic :: Software Development :: Build Tools
Classifier: Topic :: Utilities
Requires-Python: >=3.8
License-File: LICENSE
Requires-Dist: requests
Requires-Dist: pyyaml
Dynamic: license-file
